{"akb":"boolean","elb":"touchstart","skb":"menuitemradio","vlb":"height","Fkb":"com.google.gwt.core.client","Nmb":"Dark","inb":"com.markmclaren.whiteboard.client.view.controller","Omb":"Toggle Dark Mode","jkb":"alertdialog","dlb":"mousedown","wnb":"com.markmclaren.whiteboard.shared.util","Mmb":"Users","rkb":"menuitemcheckbox","Rkb":"CSS1Compat","Akb":"com.google.gwt.user.client.ui","knb":"xFine","ckb":"function","Mkb":"com.google.gwt.core.client.impl","ilb":"com.google.gwt.http.client","Lmb":"Toggle fullscreen mode","Kkb":"__java$exception","Okb":"fnStack","jlb":"callback","ekb":"java.lang","Qlb":"com.google.gwt.user.client.impl","Ikb":"top","Plb":"__uiObjectID","rmb":"Normal","Vmb":"Fine","znb":"malformed input around byte ","xkb":"radiogroup","Jlb":"touchcancel","umb":"FillTool","zmb":"PencilBlack","Pmb":"Let other people view the whiteboard","HL":"https://s1.whiteboardfox.com/","Ukb":"hidden","Dmb":"%) hue-rotate(","Zmb":"#FFFFFF88","Unb":"java.util.stream","Jmb":"Select","dnb":"com.markmclaren.whiteboard.client.view","Qmb":"Post","clb":"com.google.gwt.event.dom.client","alb":"com.google.web.bindery.event.shared","xlb":"com.google.gwt.logging.client","kkb":"application","tkb":"navigation","okb":"complementary","flb":"com.google.gwt.event.logical.shared","$lb":"com.google.gwt.user.client.ui.impl","Anb":"com.markmclaren.whiteboard.shared.util.io","gkb":"com.google.gwt.animation.client","rnb":"com.markmclaren.whiteboard.shared","cmb":").\\n","Fmb":"brightness(","Ekb":"com.google.gwt.canvas.client","blb":"com.google.gwt.event.shared","Ymb":"Connection to server was lost - please refresh page to reconnect","ynb":"malformed input: partial character at end","WD":"","cnb":"Error uploading image file","wkb":"progressbar","zlb":"SEVERE","dmb":"Expect more errors.","rlb":"com.google.gwt.layout.client","hlb":"UmbrellaException","bkb":"number","jmb":"28px Arial","Emb":"deg) ","hnb":"Element not supported ","Flb":"mouseout","mnb":"Jumbo","Gmb":"%) contrast(","Nkb":"anonymous","qmb":"Freestyle","ikb":"com.google.gwt.aria.client","Dlb":"com.google.gwt.safehtml.shared","omb":"Exception in click to fill: ","pkb":"contentinfo","ukb":"presentation","vmb":"Copy command is disabled, please ask the owner of this whiteboard to enable the Copy feature for all participants","fI":"gwt-ToggleButton","ylb":"com.google.gwt.logging.impl","nkb":"columnheader","vkb":"null","mkb":"button","fmb":"com.markmclaren.whiteboard.client","pmb":"fileUpload","Hmb":"%); opacity:","imb":"white","Smb":", ","Jkb":"__noinit__","wlb":"java.util.logging","Bmb":"%) sepia(","Kmb":"Fullscreen","slb":"left","bmb":"Possible problem with your *.gwt.xml module file.\\nThe compile time user.agent value (safari) does not match the runtime user.agent value (","Ckb":"disabled","tmb":"Reposition the view (Key A + Drag Mouse)","Ynb":"Index: ","ulb":"right","Olb":"__gwtLastUnhandledEvent","onb":"com.markmclaren.whiteboard.fill","Gkb":"com.google.gwt.canvas.dom.client","_lb":"safari","qkb":"definition","Pkb":"Unknown","ymb":"/><br/>","Qkb":"com.google.gwt.dom.client","Vkb":"load","Rnb":", length: ","tlb":"0.0px","hkb":"com.google.gwt.user.client","Cmb":"saturate(","lmb":"14px Arial","unb":"java.util","Wnb":"javaemul.internal","Dnb":"For input string: \"","Tkb":"absolute","Qnb":"fromIndex: 0, toIndex: ","Skb":"position","Onb":"delete","smb":"Move","Snb":"java.util.function","Znb":", Size: ","Imb":"Focus on a larger whiteboard area (Scroll Mouse Wheel)","Xnb":"Invalid UTF8 sequence","Xmb":"iphone","lnb":"Thick","Umb":"Rectangle","ykb":"spinbutton","zkb":"aria-hidden","Hkb":"bottom","$strongName":"4767A6E0C98FE8EDA5AE0BA8F505BE97","_jb":"object","Tmb":"Unknown ShapeType: ","kmb":"bold 16px Arial","enb":"com.markmclaren.whiteboard.shared.diagram","Rmb":"Post a snapshot to my gallery","Blb":"java.io","$nb":"fromIndex: "}